meya_cli/__init__.py
meya_cli/base_command.py
meya_cli/cat_command.py
meya_cli/delete_command.py
meya_cli/download_command.py
meya_cli/fs_events.py
meya_cli/init_command.py
meya_cli/list_command.py
meya_cli/meya_api.py
meya_cli/meya_cli.py
meya_cli/meya_config.py
meya_cli/path_utils.py
meya_cli/upload_command.py
meya_cli/watch_command.py
meya_cli-1.0.6.dist-info/METADATA
meya_cli-1.0.6.dist-info/RECORD
meya_cli-1.0.6.dist-info/WHEEL
meya_cli-1.0.6.dist-info/entry_points.txt
meya_cli-1.0.6.dist-info/top_level.txt
