Metadata-Version: 2.1
Name: meya-cli
Version: 1.0.6
Summary: Manage Meya bots from command-line.
Home-page: UNKNOWN
Author: Meya.ai
Author-email: support@meya.ai
License: Apache License 2.0
Platform: UNKNOWN
Requires-Dist: watchdog (>=0.8.3)
Requires-Dist: requests (>=2.18.4)
Requires-Dist: poyo (>=0.4.1)
